spectrseqtools/__init__.py
spectrseqtools/cli.py
spectrseqtools/common.py
spectrseqtools/deconvolution.py
spectrseqtools/fragment_classification.py
spectrseqtools/linear_program.py
spectrseqtools/mass_explanation.py
spectrseqtools/mass_table.py
spectrseqtools/masses.py
spectrseqtools/plotting.py
spectrseqtools/prediction.py
spectrseqtools/preprocessing.py
spectrseqtools/singleton_identification.py
spectrseqtools/skeleton_building.py
spectrseqtools/utils.py
spectrseqtools/assets/element_masses.tsv
spectrseqtools/assets/elemental_composition.tsv
spectrseqtools/assets/masses.tsv
spectrseqtools-0.1.2.dist-info/METADATA
spectrseqtools-0.1.2.dist-info/WHEEL
spectrseqtools-0.1.2.dist-info/entry_points.txt
spectrseqtools-0.1.2.dist-info/licenses/LICENSE
spectrseqtools-0.1.2.dist-info/RECORD
